odoo/addons/sale_blanket_order_line_description/LICENSE
odoo/addons/sale_blanket_order_line_description/README.rst
odoo/addons/sale_blanket_order_line_description/__init__.py
odoo/addons/sale_blanket_order_line_description/__manifest__.py
odoo/addons/sale_blanket_order_line_description/images/screen.png
odoo/addons/sale_blanket_order_line_description/models/__init__.py
odoo/addons/sale_blanket_order_line_description/models/blanket_order.py
odoo/addons/sale_blanket_order_line_description/static/description/icon.png
odoo/addons/sale_blanket_order_line_description/static/description/index.html
odoo/addons/sale_blanket_order_line_description/tests/TEST_INSTRUCTIONS.rst
odoo/addons/sale_blanket_order_line_description/views/view_blanket_order_form.xml
odoo/addons/sale_blanket_order_line_description/wizard/__init__.py
odoo/addons/sale_blanket_order_line_description/wizard/create_sale_orders.py
odoo_addon_sale_blanket_order_line_description-16.0.1.0.0.dist-info/METADATA
odoo_addon_sale_blanket_order_line_description-16.0.1.0.0.dist-info/WHEEL
odoo_addon_sale_blanket_order_line_description-16.0.1.0.0.dist-info/top_level.txt
odoo_addon_sale_blanket_order_line_description-16.0.1.0.0.dist-info/RECORD
